alicorn/__init__.py
alicorn/__main__.py
alicorn/_config.py
alicorn/_core.py
alicorn/_ctx.py
alicorn/_rpc.py
alicorn/_run.py
alicorn/_type.py
alicorn/_version.py
alicorn/dependency.py
alicorn/discover.py
alicorn/exception.py
alicorn/extension.py
alicorn/port.py
alicorn/signal.py
alicorn/util.py
alicorn/ext/__init__.py
alicorn/ext/leak.py
alicorn/ext/logging.py
alicorn-0.0.3.dist-info/LICENSE
alicorn-0.0.3.dist-info/METADATA
alicorn-0.0.3.dist-info/WHEEL
alicorn-0.0.3.dist-info/top_level.txt
alicorn-0.0.3.dist-info/RECORD
