Metadata-Version: 2.1
Name: alicorn
Version: 0.0.3
Summary: A grpc framework
Home-page: https://gitlab.com/cstranex/alicorn
Author: Chris Stranex
Author-email: chris@stranex.com
License: UNKNOWN
Project-URL: Source Code, https://gitlab.com/cstranex/alicorn
Project-URL: Documentation, https://cstranex.gitlab.io/alicorn/
Platform: UNKNOWN
Classifier: Programming Language :: Python :: 3
Classifier: License :: OSI Approved :: Apache Software License
Classifier: Operating System :: OS Independent
Classifier: Development Status :: 3 - Alpha
Classifier: Environment :: Web Environment
Classifier: Topic :: Software Development :: Libraries :: Application Frameworks
Classifier: Intended Audience :: Developers
Requires-Python: >=3.7
Requires-Dist: grpcio (>=1.29.0)
Requires-Dist: protobuf (>=3.10)
